DFRobot_siot/__init__.py
DFRobot_siot/getsub.py
DFRobot_siot/pub.py
DFRobot_siot/pub_sub.py
DFRobot_siot/siot.py
DFRobot_siot/sub.py
DFRobot_siot-0.0.1.dist-info/LICENCE
DFRobot_siot-0.0.1.dist-info/METADATA
DFRobot_siot-0.0.1.dist-info/WHEEL
DFRobot_siot-0.0.1.dist-info/top_level.txt
DFRobot_siot-0.0.1.dist-info/RECORD
