Metadata-Version: 2.1
Name: DFRobot-siot
Version: 0.0.1
Summary: A package for siot publish and subscribe
Home-page: https://github.com/luoyufenglalala/DFRobot_siot
Author: luoyufenglalala
Author-email: yufeng.luo@dfrobot.com
License: UNKNOWN
Platform: UNKNOWN
Classifier: Programming Language :: Python :: 3
Classifier: License :: OSI Approved :: MIT License
Classifier: Operating System :: OS Independent
Requires-Python: >=3.6
